jaxfin/__init__.py
jaxfin/py.typed
jaxfin/models/__init__.py
jaxfin/models/utils.py
jaxfin/models/gbm/__init__.py
jaxfin/models/gbm/gbm.py
jaxfin/models/heston/__init__.py
jaxfin/models/heston/heston.py
jaxfin/price_engine/__init__.py
jaxfin/price_engine/black/__init__.py
jaxfin/price_engine/black/black_model.py
jaxfin/price_engine/black_scholes/__init__.py
jaxfin/price_engine/black_scholes/vanilla_options.py
jaxfin/price_engine/fft/__init__.py
jaxfin/price_engine/fft/vanilla_options.py
jaxfin/price_engine/math/__init__.py
jaxfin/price_engine/math/bs_common.py
jaxfin/price_engine/math/norm.py
jaxfin/price_engine/utils/__init__.py
jaxfin/price_engine/utils/arrays.py
jaxfin/price_engine/utils/vect.py
JaxFin-0.3.3.dist-info/LICENSE
JaxFin-0.3.3.dist-info/METADATA
JaxFin-0.3.3.dist-info/WHEEL
JaxFin-0.3.3.dist-info/top_level.txt
JaxFin-0.3.3.dist-info/RECORD
