Metadata-Version: 2.1
Name: JaxFin
Version: 0.3.3
Summary: JaxFin is a powerful and versatile Python library designed for pricing exotic options using a range of advanced financial techniques.
Author-email: Paolo D'Elia <paolo.delia99@gmail.com>, Samuele D'Elia <delia.samuele00@gmail.com>
Classifier: Programming Language :: Python :: 3
Classifier: License :: OSI Approved :: MIT License
Classifier: Operating System :: OS Independent
Classifier: Topic :: Scientific/Engineering :: Mathematics
Classifier: Topic :: Software Development :: Libraries :: Python Modules
Classifier: Intended Audience :: Financial and Insurance Industry
Classifier: Intended Audience :: Education
Classifier: Intended Audience :: Developers
Requires-Python: >=3.10
License-File: LICENSE
Requires-Dist: jax ==0.4.23
Requires-Dist: jaxlib ==0.4.23
